Workbook

Sheet Dashboard
B1: 🎯 RFM CUSTOMER SEGMENTATION DASHBOARD | Online Retail | Dec 2010 – Dec 2011
B2: Reference Date: 10-Dec-2011 • 4,338 Customers • 397,884 Clean Transactions • Data: UCI Online Retail Dataset
B5: 👥 Total Customers | F5: 💰 Total Revenue | J5: 📅 Avg Recency (Days) | N5: 🔁 Avg Frequency | R5: 💳 Avg Spend/Customer
B6: =COUNTA('RFM Metrics'!A3:A4340) | F6: =SUM('RFM Metrics'!E3:E4340) | J6: =ROUND(AVERAGE('RFM Metrics'!C3:C4340),0) | N6: =ROUND(AVERAGE('RFM Metrics'!D3:D4340),1) | R6: =IFERROR(SUM('RFM Metrics'!E3:E4340)/COUNTA('RFM Metrics'!A3:A4340),0)
B8: FY2011 dataset | F8: FY2011 dataset | J8: FY2011 dataset | N8: FY2011 dataset | R8: FY2011 dataset
B10: 📋 SEGMENT BREAKDOWN | K10: 💡 REVENUE OPPORTUNITY SIGNALS
B11: Segment | C11: Customers | D11: Revenue (£) | E11: Avg Recency | F11: Avg Monetary | G11: % Customers | H11: % Revenue | I11: Action | K11: 🚨 At Risk Revenue Exposure | O11: =SUMIF('RFM Metrics'!J3:J4340,"At Risk",'RFM Metrics'!E3:E4340)
B12: Champions | C12: =COUNTIF('RFM Metrics'!J3:J4340,B12) | D12: =SUMIF('RFM Metrics'!J3:J4340,B12,'RFM Metrics'!E3:E4340) | E12: =IFERROR(AVERAGEIF('RFM Metrics'!J3:J4340,B12,'RFM Metrics'!C3:C4340),0) | F12: =IFERROR(AVERAGEIF('RFM Metrics'!J3:J4340,B12,'RFM Metrics'!E3:E4340),0) | G12: =IFERROR(C12/COUNTA('RFM Metrics'!A3:A4340),0) | H12: =IFERROR(D12/SUM('RFM Metrics'!E3:E4340),0) | I12: 🎁 VIP Reward + Referral | K12: 💀 Lost Revenue Exposure | O12: =SUMIF('RFM Metrics'!J3:J4340,"Lost",'RFM Metrics'!E3:E4340)
B13: Loyal Customers | C13: =COUNTIF('RFM Metrics'!J3:J4340,B13) | D13: =SUMIF('RFM Metrics'!J3:J4340,B13,'RFM Metrics'!E3:E4340) | E13: =IFERROR(AVERAGEIF('RFM Metrics'!J3:J4340,B13,'RFM Metrics'!C3:C4340),0) | F13: =IFERROR(AVERAGEIF('RFM Metrics'!J3:J4340,B13,'RFM Metrics'!E3:E4340),0) | G13: =IFERROR(C13/COUNTA('RFM Metrics'!A3:A4340),0) | H13: =IFERROR(D13/SUM('RFM Metrics'!E3:E4340),0) | I13: ⭐ Loyalty Points + Upsell | K13: 🏆 Champions Revenue | O13: =SUMIF('RFM Metrics'!J3:J4340,"Champions",'RFM Metrics'!E3:E4340)
B14: Potential Loyalist | C14: =COUNTIF('RFM Metrics'!J3:J4340,B14) | D14: =SUMIF('RFM Metrics'!J3:J4340,B14,'RFM Metrics'!E3:E4340) | E14: =IFERROR(AVERAGEIF('RFM Metrics'!J3:J4340,B14,'RFM Metrics'!C3:C4340),0) | F14: =IFERROR(AVERAGEIF('RFM Metrics'!J3:J4340,B14,'RFM Metrics'!E3:E4340),0) | G14: =IFERROR(C14/COUNTA('RFM Metrics'!A3:A4340),0) | H14: =IFERROR(D14/SUM('RFM Metrics'!E3:E4340),0) | I14: 💌 Nurture Campaign | K14: 🔁 Total Win-Back Opportunity | O14: =SUMIF('RFM Metrics'!J3:J4340,"At Risk",'RFM Metrics'!E3:E4340)+SUMIF('RFM Metrics'!J3:J4340,"Lost",'RFM Metrics'!E3:E4340)
B15: Promising | C15: =COUNTIF('RFM Metrics'!J3:J4340,B15) | D15: =SUMIF('RFM Metrics'!J3:J4340,B15,'RFM Metrics'!E3:E4340) | E15: =IFERROR(AVERAGEIF('RFM Metrics'!J3:J4340,B15,'RFM Metrics'!C3:C4340),0) | F15: =IFERROR(AVERAGEIF('RFM Metrics'!J3:J4340,B15,'RFM Metrics'!E3:E4340),0) | G15: =IFERROR(C15/COUNTA('RFM Metrics'!A3:A4340),0) | H15: =IFERROR(D15/SUM('RFM Metrics'!E3:E4340),0) | I15: 🎯 Second Purchase Offer | K15: 💡 Win back At Risk + Lost customers to recover the opportunity above
B16: New Customers | C16: =COUNTIF('RFM Metrics'!J3:J4340,B16) | D16: =SUMIF('RFM Metrics'!J3:J4340,B16,'RFM Metrics'!E3:E4340) | E16: =IFERROR(AVERAGEIF('RFM Metrics'!J3:J4340,B16,'RFM Metrics'!C3:C4340),0) | F16: =IFERROR(AVERAGEIF('RFM Metrics'!J3:J4340,B16,'RFM Metrics'!E3:E4340),0) | G16: =IFERROR(C16/COUNTA('RFM Metrics'!A3:A4340),0) | H16: =IFERROR(D16/SUM('RFM Metrics'!E3:E4340),0) | I16: 👋 Welcome Series | K16: 💎 REVENUE BAND DISTRIBUTION
B17: At Risk | C17: =COUNTIF('RFM Metrics'!J3:J4340,B17) | D17: =SUMIF('RFM Metrics'!J3:J4340,B17,'RFM Metrics'!E3:E4340) | E17: =IFERROR(AVERAGEIF('RFM Metrics'!J3:J4340,B17,'RFM Metrics'!C3:C4340),0) | F17: =IFERROR(AVERAGEIF('RFM Metrics'!J3:J4340,B17,'RFM Metrics'!E3:E4340),0) | G17: =IFERROR(C17/COUNTA('RFM Metrics'!A3:A4340),0) | H17: =IFERROR(D17/SUM('RFM Metrics'!E3:E4340),0) | I17: 🚨 Win-Back Email | K17: 🏆 Platinum ≥ £5,000 | O17: =COUNTIF('RFM Metrics'!K3:K4340,"🏆 Platinum")
B18: Need Attention | C18: =COUNTIF('RFM Metrics'!J3:J4340,B18) | D18: =SUMIF('RFM Metrics'!J3:J4340,B18,'RFM Metrics'!E3:E4340) | E18: =IFERROR(AVERAGEIF('RFM Metrics'!J3:J4340,B18,'RFM Metrics'!C3:C4340),0) | F18: =IFERROR(AVERAGEIF('RFM Metrics'!J3:J4340,B18,'RFM Metrics'!E3:E4340),0) | G18: =IFERROR(C18/COUNTA('RFM Metrics'!A3:A4340),0) | H18: =IFERROR(D18/SUM('RFM Metrics'!E3:E4340),0) | I18: 📧 Re-engagement Survey | K18: 🥇 Gold ≥ £2,000 | O18: =COUNTIF('RFM Metrics'!K3:K4340,"🥇 Gold")
B19: Lost | C19: =COUNTIF('RFM Metrics'!J3:J4340,B19) | D19: =SUMIF('RFM Metrics'!J3:J4340,B19,'RFM Metrics'!E3:E4340) | E19: =IFERROR(AVERAGEIF('RFM Metrics'!J3:J4340,B19,'RFM Metrics'!C3:C4340),0) | F19: =IFERROR(AVERAGEIF('RFM Metrics'!J3:J4340,B19,'RFM Metrics'!E3:E4340),0) | G19: =IFERROR(C19/COUNTA('RFM Metrics'!A3:A4340),0) | H19: =IFERROR(D19/SUM('RFM Metrics'!E3:E4340),0) | I19: 💤 Sunset / Reactivate | K19: 🥈 Silver ≥ £800 | O19: =COUNTIF('RFM Metrics'!K3:K4340,"🥈 Silver")
B20: TOTAL | C20: =SUM(C12:C19) | D20: =SUM(D12:D19) | K20: 🥉 Bronze < £800 | O20: =COUNTIF('RFM Metrics'!K3:K4340,"🥉 Bronze")
B22: 📖 HOW TO READ THIS DASHBOARD | K22: 🌍 TOP COUNTRIES BY REVENUE
B23: 🔢 R Score (Recency): | D23: 1–5. Score 5 = last purchase ≤30 days ago. Lower recency days = higher score. | K23: 🌍 United Kingdom | O23: 7308391.5
B24: 🔢 F Score (Frequency): | D24: 1–5. Score 5 = 20+ unique orders. Measures loyalty through repeat purchases. | K24: 🌍 Netherlands | O24: 285446.34
B25: 🔢 M Score (Monetary): | D25: 1–5. Score 5 = £5,000+ lifetime spend. Benchmarked to this dataset's distribution. | K25: 🌍 EIRE | O25: 265545.9
B26: 🏷️ RFM Combo: | D26: 3-digit string (e.g. 555 = Champion). Mapped via XLOOKUP to Segment Map sheet. | K26: 🌍 Germany | O26: 228867.14
B27: 🎯 Key Insight: | D27: Champions = protect & reward. At Risk = win-back urgently. Lost = reactivate or sunset. | K27: 🌍 France | O27: 209024.05
K28: 🌍 Australia | O28: 138521.31
B29: Built with Excel • UCI Online Retail Dataset • RFM Analysis • Data Analytics Portfolio • 2024

Sheet Raw Data
A1: 🛒 Online Retail Transaction Data | Dec 2010 – Dec 2011 | Sample: 5,000 rows
A2: InvoiceNo | B2: CustomerID | C2: Country | D2: StockCode | E2: Description | F2: Quantity | G2: UnitPrice | H2: Total Sales | I2: InvoiceDate
A3: 536377 | B3: 17850 | C3: United Kingdom | D3: 22633 | E3: HAND WARMER UNION JACK | F3: 6 | G3: 1.85 | H3: 11.1 | I3: 40513
A4: 536381 | B4: 15311 | C4: United Kingdom | D4: 22083 | E4: PAPER CHAIN KIT RETROSPOT | F4: 1 | G4: 2.95 | H4: 2.95 | I4: 40513
A5: 536392 | B5: 13705 | C5: United Kingdom | D5: 22827 | E5: RUSTIC SEVENTEEN DRAWER SIDEBOARD | F5: 1 | G5: 165 | H5: 165 | I5: 40513
A6: 536398 | B6: 13448 | C6: United Kingdom | D6: 22111 | E6: SCOTTIE DOG HOT WATER BOTTLE | F6: 9 | G6: 4.95 | H6: 44.55 | I6: 40513
A7: 536408 | B7: 14307 | C7: United Kingdom | D7: 21733 | E7: RED HANGING HEART T-LIGHT HOLDER | F7: 6 | G7: 2.95 | H7: 17.7 | I7: 40513
A8: 536409 | B8: 17908 | C8: United Kingdom | D8: 21866 | E8: UNION JACK FLAG LUGGAGE TAG | F8: 1 | G8: 1.25 | H8: 1.25 | I8: 40513
A9: 536412 | B9: 17920 | C9: United Kingdom | D9: 22273 | E9: FELTCRAFT DOLL MOLLY | F9: 1 | G9: 2.95 | H9: 2.95 | I9: 40513
A10: 536415 | B10: 12838 | C10: United Kingdom | D10: 22807 | E10: SET OF 6 T-LIGHTS TOADSTOOLS | F10: 12 | G10: 2.95 | H10: 35.4 | I10: 40513
A11: 536464 | B11: 17968 | C11: United Kingdom | D11: 21977 | E11: PACK OF 60 PINK PAISLEY CAKE CASES | F11: 1 | G11: 0.55 | H11: 0.55 | I11: 40513
A12: 536464 | B12: 17968 | C12: United Kingdom | D12: 22809 | E12: SET OF 6 T-LIGHTS SANTA | F12: 1 | G12: 2.95 | H12: 2.95 | I12: 40513
A13: 536477 | B13: 16210 | C13: United Kingdom | D13: 20977 | E13: 36 PENCILS TUBE WOODLAND | F13: 16 | G13: 1.25 | H13: 20 | I13: 40513
A14: 536488 | B14: 17897 | C14: United Kingdom | D14: 22961 | E14: JAM MAKING SET PRINTED | F14: 1 | G14: 1.45 | H14: 1.45 | I14: 40513
... A5002: 581587 | B5002: 12680 | C5002: France | D5002: 22555 | E5002: PLASTERS IN TIN STRONGMAN | F5002: 12 | G5002: 1.65 | H5002: 19.8 | I5002: 40886

Sheet RFM Metrics
A1: 📊 RFM Metrics & Scoring | 4,338 Customers | Reference Date: 10-Dec-2011
A2: CustomerID | B2: Country | C2: Recency (Days) | D2: Frequency (Orders) | E2: Monetary (£) | F2: R Score | G2: F Score | H2: M Score | I2: RFM Combo | J2: Segment | K2: Revenue Band | L2: Last Purchase
A3: 12346 | B3: United Kingdom | C3: 326 | D3: 1 | E3: 77183.6 | F3: =IF(C3<=30,5,IF(C3<=60,4,IF(C3<=120,3,IF(C3<=200,2,1)))) | G3: =IF(D3>=20,5,IF(D3>=10,4,IF(D3>=5,3,IF(D3>=2,2,1)))) | H3: =IF(E3>=5000,5,IF(E3>=2000,4,IF(E3>=800,3,IF(E3>=300,2,1)))) | I3: =TEXT(F3,"0")&TEXT(G3,"0")&TEXT(H3,"0") | J3: =IFERROR(XLOOKUP(I3,'Segment Map'!A:A,'Segment Map'!B:B,"Need Attention"),"Need Attention") | K3: =IF(E3>=5000,"🏆 Platinum",IF(E3>=2000,"🥇 Gold",IF(E3>=800,"🥈 Silver","🥉 Bronze"))) | L3: 40561
A4: 12347 | B4: Iceland | C4: 3 | D4: 7 | E4: 4310 | F4: =IF(C4<=30,5,IF(C4<=60,4,IF(C4<=120,3,IF(C4<=200,2,1)))) | G4: =IF(D4>=20,5,IF(D4>=10,4,IF(D4>=5,3,IF(D4>=2,2,1)))) | H4: =IF(E4>=5000,5,IF(E4>=2000,4,IF(E4>=800,3,IF(E4>=300,2,1)))) | I4: =TEXT(F4,"0")&TEXT(G4,"0")&TEXT(H4,"0") | J4: =IFERROR(XLOOKUP(I4,'Segment Map'!A:A,'Segment Map'!B:B,"Need Attention"),"Need Attention") | K4: =IF(E4>=5000,"🏆 Platinum",IF(E4>=2000,"🥇 Gold",IF(E4>=800,"🥈 Silver","🥉 Bronze"))) | L4: 40884
A5: 12348 | B5: Finland | C5: 76 | D5: 4 | E5: 1797.24 | F5: =IF(C5<=30,5,IF(C5<=60,4,IF(C5<=120,3,IF(C5<=200,2,1)))) | G5: =IF(D5>=20,5,IF(D5>=10,4,IF(D5>=5,3,IF(D5>=2,2,1)))) | H5: =IF(E5>=5000,5,IF(E5>=2000,4,IF(E5>=800,3,IF(E5>=300,2,1)))) | I5: =TEXT(F5,"0")&TEXT(G5,"0")&TEXT(H5,"0") | J5: =IFERROR(XLOOKUP(I5,'Segment Map'!A:A,'Segment Map'!B:B,"Need Attention"),"Need Attention") | K5: =IF(E5>=5000,"🏆 Platinum",IF(E5>=2000,"🥇 Gold",IF(E5>=800,"🥈 Silver","🥉 Bronze"))) | L5: 40811
A6: 12349 | B6: Italy | C6: 19 | D6: 1 | E6: 1757.55 | F6: =IF(C6<=30,5,IF(C6<=60,4,IF(C6<=120,3,IF(C6<=200,2,1)))) | G6: =IF(D6>=20,5,IF(D6>=10,4,IF(D6>=5,3,IF(D6>=2,2,1)))) | H6: =IF(E6>=5000,5,IF(E6>=2000,4,IF(E6>=800,3,IF(E6>=300,2,1)))) | I6: =TEXT(F6,"0")&TEXT(G6,"0")&TEXT(H6,"0") | J6: =IFERROR(XLOOKUP(I6,'Segment Map'!A:A,'Segment Map'!B:B,"Need Attention"),"Need Attention") | K6: =IF(E6>=5000,"🏆 Platinum",IF(E6>=2000,"🥇 Gold",IF(E6>=800,"🥈 Silver","🥉 Bronze"))) | L6: 40868
A7: 12350 | B7: Norway | C7: 311 | D7: 1 | E7: 334.4 | F7: =IF(C7<=30,5,IF(C7<=60,4,IF(C7<=120,3,IF(C7<=200,2,1)))) | G7: =IF(D7>=20,5,IF(D7>=10,4,IF(D7>=5,3,IF(D7>=2,2,1)))) | H7: =IF(E7>=5000,5,IF(E7>=2000,4,IF(E7>=800,3,IF(E7>=300,2,1)))) | I7: =TEXT(F7,"0")&TEXT(G7,"0")&TEXT(H7,"0") | J7: =IFERROR(XLOOKUP(I7,'Segment Map'!A:A,'Segment Map'!B:B,"Need Attention"),"Need Attention") | K7: =IF(E7>=5000,"🏆 Platinum",IF(E7>=2000,"🥇 Gold",IF(E7>=800,"🥈 Silver","🥉 Bronze"))) | L7: 40576
A8: 12352 | B8: Norway | C8: 37 | D8: 8 | E8: 2506.04 | F8: =IF(C8<=30,5,IF(C8<=60,4,IF(C8<=120,3,IF(C8<=200,2,1)))) | G8: =IF(D8>=20,5,IF(D8>=10,4,IF(D8>=5,3,IF(D8>=2,2,1)))) | H8: =IF(E8>=5000,5,IF(E8>=2000,4,IF(E8>=800,3,IF(E8>=300,2,1)))) | I8: =TEXT(F8,"0")&TEXT(G8,"0")&TEXT(H8,"0") | J8: =IFERROR(XLOOKUP(I8,'Segment Map'!A:A,'Segment Map'!B:B,"Need Attention"),"Need Attention") | K8: =IF(E8>=5000,"🏆 Platinum",IF(E8>=2000,"🥇 Gold",IF(E8>=800,"🥈 Silver","🥉 Bronze"))) | L8: 40850
A9: 12353 | B9: Bahrain | C9: 205 | D9: 1 | E9: 89 | F9: =IF(C9<=30,5,IF(C9<=60,4,IF(C9<=120,3,IF(C9<=200,2,1)))) | G9: =IF(D9>=20,5,IF(D9>=10,4,IF(D9>=5,3,IF(D9>=2,2,1)))) | H9: =IF(E9>=5000,5,IF(E9>=2000,4,IF(E9>=800,3,IF(E9>=300,2,1)))) | I9: =TEXT(F9,"0")&TEXT(G9,"0")&TEXT(H9,"0") | J9: =IFERROR(XLOOKUP(I9,'Segment Map'!A:A,'Segment Map'!B:B,"Need Attention"),"Need Attention") | K9: =IF(E9>=5000,"🏆 Platinum",IF(E9>=2000,"🥇 Gold",IF(E9>=800,"🥈 Silver","🥉 Bronze"))) | L9: 40682
A10: 12354 | B10: Spain | C10: 233 | D10: 1 | E10: 1079.4 | F10: =IF(C10<=30,5,IF(C10<=60,4,IF(C10<=120,3,IF(C10<=200,2,1)))) | G10: =IF(D10>=20,5,IF(D10>=10,4,IF(D10>=5,3,IF(D10>=2,2,1)))) | H10: =IF(E10>=5000,5,IF(E10>=2000,4,IF(E10>=800,3,IF(E10>=300,2,1)))) | I10: =TEXT(F10,"0")&TEXT(G10,"0")&TEXT(H10,"0") | J10: =IFERROR(XLOOKUP(I10,'Segment Map'!A:A,'Segment Map'!B:B,"Need Attention"),"Need Attention") | K10: =IF(E10>=5000,"🏆 Platinum",IF(E10>=2000,"🥇 Gold",IF(E10>=800,"🥈 Silver","🥉 Bronze"))) | L10: 40654
A11: 12355 | B11: Bahrain | C11: 215 | D11: 1 | E11: 459.4 | F11: =IF(C11<=30,5,IF(C11<=60,4,IF(C11<=120,3,IF(C11<=200,2,1)))) | G11: =IF(D11>=20,5,IF(D11>=10,4,IF(D11>=5,3,IF(D11>=2,2,1)))) | H11: =IF(E11>=5000,5,IF(E11>=2000,4,IF(E11>=800,3,IF(E11>=300,2,1)))) | I11: =TEXT(F11,"0")&TEXT(G11,"0")&TEXT(H11,"0") | J11: =IFERROR(XLOOKUP(I11,'Segment Map'!A:A,'Segment Map'!B:B,"Need Attention"),"Need Attention") | K11: =IF(E11>=5000,"🏆 Platinum",IF(E11>=2000,"🥇 Gold",IF(E11>=800,"🥈 Silver","🥉 Bronze"))) | L11: 40672
A12: 12356 | B12: Portugal | C12: 23 | D12: 3 | E12: 2811.43 | F12: =IF(C12<=30,5,IF(C12<=60,4,IF(C12<=120,3,IF(C12<=200,2,1)))) | G12: =IF(D12>=20,5,IF(D12>=10,4,IF(D12>=5,3,IF(D12>=2,2,1)))) | H12: =IF(E12>=5000,5,IF(E12>=2000,4,IF(E12>=800,3,IF(E12>=300,2,1)))) | I12: =TEXT(F12,"0")&TEXT(G12,"0")&TEXT(H12,"0") | J12: =IFERROR(XLOOKUP(I12,'Segment Map'!A:A,'Segment Map'!B:B,"Need Attention"),"Need Attention") | K12: =IF(E12>=5000,"🏆 Platinum",IF(E12>=2000,"🥇 Gold",IF(E12>=800,"🥈 Silver","🥉 Bronze"))) | L12: 40864
A13: 12357 | B13: Switzerland | C13: 34 | D13: 1 | E13: 6207.67 | F13: =IF(C13<=30,5,IF(C13<=60,4,IF(C13<=120,3,IF(C13<=200,2,1)))) | G13: =IF(D13>=20,5,IF(D13>=10,4,IF(D13>=5,3,IF(D13>=2,2,1)))) | H13: =IF(E13>=5000,5,IF(E13>=2000,4,IF(E13>=800,3,IF(E13>=300,2,1)))) | I13: =TEXT(F13,"0")&TEXT(G13,"0")&TEXT(H13,"0") | J13: =IFERROR(XLOOKUP(I13,'Segment Map'!A:A,'Segment Map'!B:B,"Need Attention"),"Need Attention") | K13: =IF(E13>=5000,"🏆 Platinum",IF(E13>=2000,"🥇 Gold",IF(E13>=800,"🥈 Silver","🥉 Bronze"))) | L13: 40853
A14: 12358 | B14: Austria | C14: 2 | D14: 2 | E14: 1168.06 | F14: =IF(C14<=30,5,IF(C14<=60,4,IF(C14<=120,3,IF(C14<=200,2,1)))) | G14: =IF(D14>=20,5,IF(D14>=10,4,IF(D14>=5,3,IF(D14>=2,2,1)))) | H14: =IF(E14>=5000,5,IF(E14>=2000,4,IF(E14>=800,3,IF(E14>=300,2,1)))) | I14: =TEXT(F14,"0")&TEXT(G14,"0")&TEXT(H14,"0") | J14: =IFERROR(XLOOKUP(I14,'Segment Map'!A:A,'Segment Map'!B:B,"Need Attention"),"Need Attention") | K14: =IF(E14>=5000,"🏆 Platinum",IF(E14>=2000,"🥇 Gold",IF(E14>=800,"🥈 Silver","🥉 Bronze"))) | L14: 40885
... A4340: 18287 | B4340: United Kingdom | C4340: 43 | D4340: 3 | E4340: 1837.28 | F4340: =IF(C4340<=30,5,IF(C4340<=60,4,IF(C4340<=120,3,IF(C4340<=200,2,1)))) | G4340: =IF(D4340>=20,5,IF(D4340>=10,4,IF(D4340>=5,3,IF(D4340>=2,2,1)))) | H4340: =IF(E4340>=5000,5,IF(E4340>=2000,4,IF(E4340>=800,3,IF(E4340>=300,2,1)))) | I4340: =TEXT(F4340,"0")&TEXT(G4340,"0")&TEXT(H4340,"0") | J4340: =IFERROR(XLOOKUP(I4340,'Segment Map'!A:A,'Segment Map'!B:B,"Need Attention"),"Need Attention") | K4340: =IF(E4340>=5000,"🏆 Platinum",IF(E4340>=2000,"🥇 Gold",IF(E4340>=800,"🥈 Silver","🥉 Bronze"))) | L4340: 40844

Sheet Segment Map
A1: 🗺️ RFM Segment Lookup Table
A2: RFM Combo | B2: Segment | C2: Recommended Action | D2: Priority | E2: Description
A3: 555 | B3: Champions | C3: VIP reward + referral program | D3: 🔴 Critical | E3: Perfect RFM — protect at all costs
A4: 554 | B4: Champions | C4: VIP reward + referral program | D4: 🔴 Critical | E4: Near-perfect — treat like Champions
A5: 545 | B5: Champions | C5: Exclusive early access + gift | D5: 🔴 Critical | E5: Very high frequency & spend
A6: 544 | B6: Champions | C6: Exclusive early access | D6: 🔴 Critical | E6: Strong all-round performers
A7: 553 | B7: Champions | C7: VIP tier upgrade | D7: 🔴 Critical | E7: High R & F, solid M
A8: 455 | B8: Loyal Customers | C8: Loyalty points + upsell higher ticket | D8: 🟠 High | E8: Recent, frequent, big spenders
A9: 454 | B9: Loyal Customers | C9: Loyalty points + upsell | D9: 🟠 High | E9: Consistent repeat buyers
A10: 445 | B10: Loyal Customers | C10: Loyalty points + upsell | D10: 🟠 High | E10: Loyal with high monetary value
A11: 444 | B11: Loyal Customers | C11: Personalised recommendations | D11: 🟠 High | E11: Solid, reliable customer base
A12: 453 | B12: Loyal Customers | C12: Category expansion offers | D12: 🟠 High | E12: Loyal with moderate monetary
A13: 355 | B13: Potential Loyalist | C13: Onboarding + engagement email series | D13: 🟡 Medium | E13: Recent with good F&M — nurture
... A40: Need Attention | B40: Need Attention | C40: General nurture campaign | D40: 🟡 Medium | E40: Catch-all for unmapped combos
